fir.v
module fir_filter (
    input clk,
    input rst,
    input [7:0] sample_in,
    output reg [15:0] sample_out
);

    reg [7:0] shift_reg[0:2];  // 3-tap delay line
    wire [15:0] mult[0:2];

    // Coefficients (e.g., h = [1, 2, 1])
    parameter h0 = 1, h1 = 2, h2 = 1;

    assign mult[0] = shift_reg[0] * h0;
    assign mult[1] = shift_reg[1] * h1;
    assign mult[2] = shift_reg[2] * h2;

    always @(posedge clk or posedge rst) begin
        if (rst) begin
            shift_reg[0] <= 0;
            shift_reg[1] <= 0;
            shift_reg[2] <= 0;
            sample_out <= 0;
        end else begin
            // Shift input samples
            shift_reg[2] <= shift_reg[1];
            shift_reg[1] <= shift_reg[0];
            shift_reg[0] <= sample_in;

            // FIR filter output
            sample_out <= mult[0] + mult[1] + mult[2];
        end
    end

endmodule

fir_tb.v
`timescale 1ns/1ps

module fir_tb;

    reg clk, rst;
    reg [7:0] sample_in;
    wire [15:0] sample_out;

    fir_filter uut (
        .clk(clk),
        .rst(rst),
        .sample_in(sample_in),
        .sample_out(sample_out)
    );

    // Clock generation
    always #5 clk = ~clk;

    initial begin
        $dumpfile("fir.vcd");
        $dumpvars(0, fir_tb);

        // Init
        clk = 0;
        rst = 1;
        sample_in = 0;

        #10 rst = 0;

        // Feed samples
        #10 sample_in = 8'd5;
        #10 sample_in = 8'd10;
        #10 sample_in = 8'd15;
        #10 sample_in = 8'd20;
        #10 sample_in = 8'd0;

        #50 $finish;
    end
endmodule

fir.vcd
$date
	Wed May 21 18:36:17 2025
$end
$version
	Icarus Verilog
$end
$timescale
	1ps
$end
$scope module fir_tb $end
$var wire 16 ! sample_out [15:0] $end
$var reg 1 " clk $end
$var reg 1 # rst $end
$var reg 8 $ sample_in [7:0] $end
$scope module uut $end
$var wire 1 " clk $end
$var wire 1 # rst $end
$var wire 8 % sample_in [7:0] $end
$var parameter 32 & h0 $end
$var parameter 32 ' h1 $end
$var parameter 32 ( h2 $end
$var reg 16 ) sample_out [15:0] $end
$upscope $end
$upscope $end
$enddefinitions $end
$comment Show the parameter values. $end
$dumpall
b1 (
b10 '
b1 &
$end
#0
$dumpvars
b0 )
b0 %
b0 $
1#
0"
b0 !
$end
#5000
1"
#10000
0"
0#
#15000
1"
#20000
0"
b101 $
b101 %
#25000
1"
#30000
0"
b1010 $
b1010 %
#35000
b101 !
b101 )
1"
#40000
0"
b1111 $
b1111 %
#45000
b10100 !
b10100 )
1"
#50000
0"
b10100 $
b10100 %
#55000
b101000 !
b101000 )
1"
#60000
0"
b0 $
b0 %
#65000
b111100 !
b111100 )
1"
#70000
0"
#75000
b110111 !
b110111 )
1"
#80000
0"
#85000
b10100 !
b10100 )
1"
#90000
0"
#95000
b0 !
b0 )
1"
